{"file":"hall_4.png","frames":{
"trading_pos_png":{"x":984,"y":135,"w":31,"h":40,"offX":9,"offY":5,"sourceW":50,"sourceH":50},
"trading_search_png":{"x":609,"y":305,"w":382,"h":48,"offX":0,"offY":0,"sourceW":382,"sourceH":48},
"item_10005_png":{"x":457,"y":247,"w":150,"h":150,"offX":0,"offY":0,"sourceW":150,"sourceH":150},
"item_10006_png":{"x":305,"y":247,"w":150,"h":150,"offX":0,"offY":0,"sourceW":150,"sourceH":150},
"item_10007_png":{"x":153,"y":247,"w":150,"h":150,"offX":0,"offY":0,"sourceW":150,"sourceH":150},
"item_10008_png":{"x":1,"y":247,"w":150,"h":150,"offX":0,"offY":0,"sourceW":150,"sourceH":150},
"item_10009_png":{"x":761,"y":153,"w":150,"h":150,"offX":0,"offY":0,"sourceW":150,"sourceH":150},
"item_10011_png":{"x":609,"y":153,"w":150,"h":150,"offX":0,"offY":0,"sourceW":150,"sourceH":150},
"item_120001_png":{"x":457,"y":95,"w":150,"h":150,"offX":0,"offY":0,"sourceW":150,"sourceH":150},
"item_120002_png":{"x":305,"y":95,"w":150,"h":150,"offX":0,"offY":0,"sourceW":150,"sourceH":150},
"item_120003_png":{"x":153,"y":95,"w":150,"h":150,"offX":0,"offY":0,"sourceW":150,"sourceH":150},
"item_120004_png":{"x":1,"y":95,"w":150,"h":150,"offX":0,"offY":0,"sourceW":150,"sourceH":150},
"item_120005_png":{"x":723,"y":1,"w":150,"h":150,"offX":0,"offY":0,"sourceW":150,"sourceH":150},
"item_bar_png":{"x":458,"y":399,"w":108,"h":43,"offX":5,"offY":2,"sourceW":118,"sourceH":49},
"item_bar_select_png":{"x":609,"y":95,"w":108,"h":43,"offX":5,"offY":2,"sourceW":118,"sourceH":49},
"star_png":{"x":568,"y":426,"w":40,"h":38,"offX":0,"offY":0,"sourceW":40,"sourceH":38},
"trade_add_png":{"x":913,"y":206,"w":69,"h":69,"offX":0,"offY":0,"sourceW":69,"sourceH":69},
"trade_coinnum_bg_png":{"x":609,"y":355,"w":221,"h":69,"offX":0,"offY":0,"sourceW":221,"sourceH":69},
"trade_done_png":{"x":875,"y":68,"w":117,"h":65,"offX":0,"offY":0,"sourceW":117,"sourceH":65},
"trade_reduce_png":{"x":913,"y":135,"w":69,"h":69,"offX":0,"offY":0,"sourceW":69,"sourceH":69},
"trade_return_png":{"x":875,"y":1,"w":117,"h":65,"offX":0,"offY":0,"sourceW":117,"sourceH":65},
"trade_selling_png":{"x":183,"y":399,"w":117,"h":65,"offX":0,"offY":0,"sourceW":117,"sourceH":65},
"trading_bottom_bar_png":{"x":1,"y":1,"w":720,"h":92,"offX":0,"offY":13,"sourceW":720,"sourceH":105},
"trading_car_tabBar1_png":{"x":302,"y":399,"w":154,"h":43,"offX":0,"offY":3,"sourceW":154,"sourceH":49},
"trading_car_tabBar2_png":{"x":832,"y":406,"w":154,"h":43,"offX":0,"offY":3,"sourceW":154,"sourceH":49},
"trading_fangchan_tabBar1_png":{"x":1,"y":399,"w":180,"h":49,"offX":2,"offY":0,"sourceW":183,"sourceH":49},
"trading_fangchan_tabBar2_png":{"x":832,"y":355,"w":180,"h":49,"offX":2,"offY":0,"sourceW":183,"sourceH":49}}}