{
	"Tool": "github.com/davyxu/tabtoy",
	"Version": "2.8.10",
	"TSkill":[
		{ "Id": 1, "Type": 1, "Num": 1, "Des": "<font color=\"#5e78f7\">贯穿弹</font>;<font color=\"#f96918\">+1</font>" },
		{ "Id": 2, "Type": 2, "Num": 2, "Des": "<font color=\"#5e78f7\">双倍时间</font>;<font color=\"#f96918\">+2s</font>" },
		{ "Id": 3, "Type": 3, "NumPer": 5, "Des": "<font color=\"#5e78f7\">大招所需能量</font>;<font color=\"#f96918\">-5%</font>" },
		{ "Id": 4, "Type": 4, "NumPer": 5, "Des": "<font color=\"#5e78f7\">金币奖励</font>;<font color=\"#f96918\">+5%</font>" },
		{ "Id": 5, "Type": 5, "NumPer": 5, "Des": "<font color=\"#5e78f7\">事件间隔时间</font>;<font color=\"#f96918\">+5%</font>" },
		{ "Id": 6, "Type": 1, "Num": 2, "Des": "<font color=\"#5e78f7\">贯穿弹</font>;<font color=\"#f96918\">+2</font>" },
		{ "Id": 7, "Type": 2, "Num": 4, "Des": "<font color=\"#5e78f7\">双倍时间</font>;<font color=\"#f96918\">+4s</font>" },
		{ "Id": 8, "Type": 3, "NumPer": 10, "Des": "<font color=\"#5e78f7\">大招所需能量</font>;<font color=\"#f96918\">-10%</font>" },
		{ "Id": 9, "Type": 4, "NumPer": 10, "Des": "<font color=\"#5e78f7\">金币奖励</font>;<font color=\"#f96918\">+10%</font>" },
		{ "Id": 10, "Type": 5, "NumPer": 10, "Des": "<font color=\"#5e78f7\">事件间隔时间</font>;<font color=\"#f96918\">+10%</font>" }
	]}